authbaserepositorys/__init__.py
authbaserepositorys/auth_middleweare/auth.py
authbaserepositorys/base_repo/base_repo.py
authbaserepositorys-0.1.0.dist-info/METADATA
authbaserepositorys-0.1.0.dist-info/WHEEL
authbaserepositorys-0.1.0.dist-info/RECORD
