Metadata-Version: 2.1
Name: authbaserepositorys
Version: 0.1.0
Summary: 
Author: Your Name
Author-email: you@example.com
Requires-Python: >=3.11,<4.0
Classifier: Programming Language :: Python :: 3
Classifier: Programming Language :: Python :: 3.11
Requires-Dist: fastapi-jwt-auth (>=0.5.0,<0.6.0)
Requires-Dist: sqlalchemy (==1.4.41)
